{
  "data": {},
  "id": "tenant1_fsm",
  "module": "Elixir.FSM.SmartDoor",
  "metadata": {
    "version": 1,
    "created_at": "2025-08-17T21:11:13.665234Z",
    "updated_at": "2025-08-17T21:11:13.665260Z",
    "tags": []
  },
  "plugins": [
    {
      "module": "Elixir.FSM.Plugins.Logger",
      "opts": {
        "level": "debug"
      }
    },
    {
      "module": "Elixir.FSM.Plugins.Audit",
      "opts": {}
    }
  ],
  "tenant_id": "tenant1",
  "current_state": "closed",
  "performance": {
    "transition_count": 0,
    "last_transition_at": null,
    "avg_transition_time": 0
  },
  "subscribers": []
}