{
  "data": {
    "raise": true
  },
  "id": "1298a15c-c270-421a-8677-7a61967bbabf",
  "module": "Elixir.FSM.HardeningTest.TestFSM",
  "metadata": {
    "version": 1,
    "created_at": "2025-08-14T19:36:55.067823Z",
    "updated_at": "2025-08-14T19:36:55.074411Z",
    "tags": []
  },
  "plugins": [],
  "tenant_id": "t-sub",
  "current_state": "active",
  "performance": {
    "transition_count": 1,
    "last_transition_at": "2025-08-14T19:36:55.074417Z",
    "avg_transition_time": 13.0
  },
  "subscribers": [
    "3fbe2a00-f36e-4627-817b-62e2cc2c4486",
    "5567c703-94e2-4da9-af5e-9b22a5579774"
  ]
}